Metadata-Version: 2.1
Name: ParseRawHTTP
Version: 1.0
Summary: Load HTTP request from a raw HTTP request
Home-page: https://github.com/Bronya-Rayi/ParseRawHTTP
Author: Rayi
Author-email: 931470970@qq.com
License: MIT
Keywords: ParseRawHTTP
Platform: all
Classifier: Programming Language :: Python :: 3
